{
    "subtitles": [
        "Competitive Programmer",
        "Software Engineer",
        "MERN Stack Developer",
        "Malviyan",
        "Lucknowite",
        "Problem Solver"
    ],
    "projects": [
        {
            "title": "MMMUT CGPA Calculator",
            "desc": "An interactive website made using HTML5, CSS, JS and Bootstrap to calculate the CGPA and SGPA of MMMUT B.Tech. students of MMMUT used by over  600+ people. ",
            "img": "cgpacalculator.png",
            "link": "https://codersaty.github.io/cgpacalculator/"
        },
        {
            "title": "Level 0 Portfolio",
            "desc": "Created an interactive website from scratch using HTML5 and CSS to list all the projects developed as a beginner while learning any new technology The website lists 10+ projects as well as 30+ blogs on Web Development and Data Structure. Tech Used: HTML , CSS , JavaScript, Nodejs , Reactjs , jQuery ",
            "img": "level0Portfolio.PNG",
            "link": "https://codersaty.netlify.app/"
        },
        {
            "title": "Diary Web App",
            "desc": "Created a web app using Nodejs and express for back-end in which a user can create, read, update and delete (CRUD) a blog. Designed the front end using technologies like Bootstrap, HTML, CSS and templating language EJS. Tech Used: HTML , CSS , Bootstrap , EJS , Nodejs , Express. (The project is in the development phase)",
            "img": "DiaryWebApp.PNG",
            "link": "https://guarded-reef-52186.herokuapp.com/"
        },
        {
            "title": "Working on it",
            "desc": "I am learning something new. If you have an idea or wanna build something together ping me. Let's build something great together.",
            "img": "construction.png",
            "link": "https://codersaty.github.io"
        }
    ],
    "skills": [
        {
            "name": "Data-Structure",
            "desc": "Design & Analysis of Algorithms",
            "per": "★★★★☆"
        },
        {
            "name": "cp",
            "desc": "Data Structure",
            "per": "★★★☆☆"
        },
        {
            "name": "web",
            "desc": "Object-oriented programming",
            "per": "★★★★☆"
        },
        {
            "name": "dbms",
            "desc": "Database Management System",
            "per": "★★★☆☆"
        },
        {
            "name": "os",
            "desc": "Principles of Operating Systems",
            "per": "★★★☆☆"
        }
    ],
    "langauge": [
        {
            "name": "c",
            "desc": "C Langauge",
            "per": "★★★★☆"
        },
        {
            "name": "cpp",
            "desc": "C++ Langauge",
            "per": "★★★★★"
        },
        {
            "name": "js",
            "desc": "JavaScript",
            "per": "★★★☆☆"
        },
        {
            "name": "sql",
            "desc": "Structured Query Language",
            "per": "★★★☆☆"
        }
    ],
    "development": [
        {
            "name": "html",
            "desc": "Hypertext Markup Language",
            "per": "★★★★☆"
        },
        {
            "name": "css",
            "desc": "Cascading Style Sheets",
            "per": "★★★☆☆"
        },
        {
            "name": "bootstrap",
            "desc": "Bootstrap",
            "per": "★★★★☆"
        },
        {
            "name": "react",
            "desc": "React",
            "per": "★★★☆☆"
        },
        {
            "name": "jquery",
            "desc": "Jquery",
            "per": "★★★☆☆"
        },
        {
            "name": "markdown",
            "desc": "Markdown",
            "per": "★★★☆☆"
        },
        {
            "name": "mongodb",
            "desc": "MongoDB",
            "per": "★★★☆☆"
        },
        {
            "name": "express",
            "desc": "Express",
            "per": "★★★☆☆"
        },
        {
            "name": "nodejs",
            "desc": "Node.js",
            "per": "★★★☆☆"
        }
    ],
    "tools": [
        {
            "name": "git",
            "desc": "Git",
            "per": "★★★☆☆"
        },
        {
            "name": "github",
            "desc": "Github",
            "per": "★★★★☆"
        },
        {
            "name": "office",
            "desc": "MS-Office",
            "per": "★★★★☆"
        },
        {
            "name": "vscode",
            "desc": "VS-Code",
            "per": "★★★★☆"
        }
    ],
    "exp": [
        {
            "name": "geeks",
            "pos": "Intern",
            "time": "Mar 2021-present",
            "des": "Coordinated with the Technical Content Engineers team at GeeksforGeeks. Wrote 50+ and improved 30+ articles on Web Development, Data Structures and Algorithms",
            "link": "https://auth.geeksforgeeks.org/user/CoderSaty/articles"
        },
        {
            "name": "chapter",
            "pos": "Competitive Programing Lead",
            "time": "Nov 2020-May 2021",
            "des": "Coordinated with Codechef to start a coding club for our college to improve the programming and coding culture of the college, which helped 100+ juniors to start their coding journey. Established a community of 350+ members on Telegram and 175+ subscribers on YouTube",
            "link": "https://chefmmmutchapter.tech/"
        },
        {
            "name": "ces",
            "pos": "Executive Member",
            "time": "Jul 2019 - May 2020",
            "des": "As an Executive member of this society we organize different college level events related to computer science and engineering. We organize all this events under the two main events MATRIX and ENNEXUS",
            "link": "https://www.linkedin.com/company/cesmmmut/"
        },
        {
            "name": "hire",
            "pos": "Hire Me",
            "des": "I am team-oriented, hardworking individual willing to give my 100% for the organization and grow together with the organization. If you think I am a right fit for your organization I will be very happy to work in the organization.",
            "link": "https://drive.google.com/file/d/1TbSyNmkMR0ddEJvbUceXWDjFbSVzSss7/view"
        }
    ],
    "blog": [
        {
            "title": "Web Development Blogs",
            "img": "blog4.png",
            "link": "https://qdl0f.csb.app/"
        },
        {
            "title": "DSA and Programming Blogs",
            "img": "blog1.PNG",
            "link": "https://v2gbv.csb.app/"
        },
        {
            "title": "All GeeksforGeeks Articles",
            "img": "blog5.png",
            "link": "https://auth.geeksforgeeks.org/user/CoderSaty/articles"
        },
        {
            "title": "My Quora Answers",
            "img": "blog3.PNG",
            "link": "https://www.quora.com/profile/Anuranjan-Srivastava-7"
        }
    ]
}